runtypecheck-0.1.1.dist-info/licenses/LICENSE
typecheck/__init__.py
typecheck/config.py
typecheck/error_utils.py
typecheck/py.typed
typecheck/type_validators.py
typecheck/utils.py
typecheck/validators.py
typecheck/weak_lru.py
runtypecheck-0.1.1.dist-info/METADATA
runtypecheck-0.1.1.dist-info/WHEEL
runtypecheck-0.1.1.dist-info/top_level.txt
runtypecheck-0.1.1.dist-info/RECORD
